{
    "circuit": [
        {
            "gate": "H",
            "qubits": [
                "Q0"
            ],
            "time": 1
        },
        {
            "gate": "CNOT",
            "qubits": [
                "Q0",
                "Q2"
            ],
            "time": 2
        },
        {
            "gate": "X",
            "qubits": [
                "Q2"
            ],
            "time": 3
        },
        {
            "gate": "Measure",
            "qubits": [
                "Q0"
            ],
            "time": 4
        },
        {
            "gate": "Hadamard",
            "qubits": [
                "Q1"
            ],
            "time": 5
        },
        {
            "gate": "CNOT",
            "qubits": [
                "Q1",
                "Q3"
            ],
            "time": 6
        },
        {
            "gate": "X",
            "qubits": [
                "Q3"
            ],
            "time": 7
        },
        {
            "gate": "Measure",
            "qubits": [
                "Q1"
            ],
            "time": 8
        },
        {
            "gate": "CNOT",
            "qubits": [
                "Q2",
                "Q4"
            ],
            "time": 9
        },
        {
            "gate": "Hadamard",
            "qubits": [
                "Q3"
            ],
            "time": 10
        },
        {
            "gate": "SWAP",
            "qubits": [
                "Q4",
                "Q6"
            ],
            "time": 11
        },
        {
            "gate": "X",
            "qubits": [
                "Q6"
            ],
            "time": 12
        },
        {
            "gate": "Measure",
            "qubits": [
                "Q2"
            ],
            "time": 13
        },
        {
            "gate": "CNOT",
            "qubits": [
                "Q0",
                "Q6"
            ],
            "time": 14
        },
        {
            "gate": "Hadamard",
            "qubits": [
                "Q5"
            ],
            "time": 15
        },
        {
            "gate": "SWAP",
            "qubits": [
                "Q6",
                "Q8"
            ],
            "time": 16
        },
        {
            "gate": "X",
            "qubits": [
                "Q7"
            ],
            "time": 17
        },
        {
            "gate": "Measure",
            "qubits": [
                "Q0"
            ],
            "time": 18
        },
        {
            "gate": "CNOT",
            "qubits": [
                "Q2",
                "Q8"
            ],
            "time": 19
        },
        {
            "gate": "Hadamard",
            "qubits": [
                "Q7"
            ],
            "time": 20
        },
        {
            "gate": "SWAP",
            "qubits": [
                "Q8",
                "Q9"
            ],
            "time": 21
        },
        {
            "gate": "X",
            "qubits": [
                "Q9"
            ],
            "time": 22
        },
        {
            "gate": "Measure",
            "qubits": [
                "Q1"
            ],
            "time": 23
        },
        {
            "gate": "CNOT",
            "qubits": [
                "Q3",
                "Q8"
            ],
            "time": 24
        },
        {
            "gate": "Hadamard",
            "qubits": [
                "Q7"
            ],
            "time": 25
        },
        {
            "gate": "SWAP",
            "qubits": [
                "Q8",
                "Q9"
            ],
            "time": 26
        },
        {
            "gate": "X",
            "qubits": [
                "Q9"
            ],
            "time": 27
        },
        {
            "gate": "Measure",
            "qubits": [
                "Q2"
            ],
            "time": 28
        },
        {
            "gate": "CNOT",
            "qubits": [
                "Q0",
                "Q8"
            ],
            "time": 29
        }
    ],
    "result": false,
    "fullOutput": {
        "valid_output_structure": true,
        "valid_gate_types": false,
        "valid_qubits": true,
        "valid_dag": true,
        "valid_gate_precedences": true,
        "valid_cnot_adjacency": true,
        "valid_swap_constraints": false,
        "valid_measurements": false,
        "valid_gate_restrictions": true,
        "layered_operations": true,
        "depth_constraint": true,
        "gate_optimization": true,
        "final_state_compliance": false,
        "errors": [
            "Invalid gate type 'Hadamard' at index 4. Allowed gates: {'H', 'X', 'Z', 'SWAP', 'CNOT', 'Measure'}.",
            "Invalid gate type 'Hadamard' at index 9. Allowed gates: {'H', 'X', 'Z', 'SWAP', 'CNOT', 'Measure'}.",
            "Invalid gate type 'Hadamard' at index 14. Allowed gates: {'H', 'X', 'Z', 'SWAP', 'CNOT', 'Measure'}.",
            "Invalid gate type 'Hadamard' at index 19. Allowed gates: {'H', 'X', 'Z', 'SWAP', 'CNOT', 'Measure'}.",
            "Invalid gate type 'Hadamard' at index 24. Allowed gates: {'H', 'X', 'Z', 'SWAP', 'CNOT', 'Measure'}.",
            "SWAP gate at index 10 operates on qubits 'Q4' and 'Q6' with differing gate sequences up to this point.",
            "Qubit 'Q0' has been measured 2 times; only one measurement allowed.",
            "Qubit 'Q1' has been measured 2 times; only one measurement allowed.",
            "Qubit 'Q2' has been measured 2 times; only one measurement allowed.",
            "Qubit 'Q0' does not end with a Measurement or a gate to reset to |0\u27e9.",
            "Qubit 'Q3' does not end with a Measurement or a gate to reset to |0\u27e9.",
            "Qubit 'Q4' does not end with a Measurement or a gate to reset to |0\u27e9.",
            "Qubit 'Q6' does not end with a Measurement or a gate to reset to |0\u27e9.",
            "Qubit 'Q5' does not end with a Measurement or a gate to reset to |0\u27e9.",
            "Qubit 'Q8' does not end with a Measurement or a gate to reset to |0\u27e9.",
            "Qubit 'Q7' does not end with a Measurement or a gate to reset to |0\u27e9."
        ],
        "overall_passed": false
    }
}