{
    "users": [
        {
            "id": "U0",
            "trust_score": 81,
            "category": "celebrity"
        },
        {
            "id": "U1",
            "trust_score": 85,
            "category": "celebrity"
        },
        {
            "id": "U2",
            "trust_score": 90,
            "category": "celebrity"
        },
        {
            "id": "U3",
            "trust_score": 95,
            "category": "celebrity"
        },
        {
            "id": "U4",
            "trust_score": 70,
            "category": "expert"
        },
        {
            "id": "U5",
            "trust_score": 73,
            "category": "expert"
        },
        {
            "id": "U6",
            "trust_score": 76,
            "category": "expert"
        },
        {
            "id": "U7",
            "trust_score": 79,
            "category": "expert"
        },
        {
            "id": "U8",
            "trust_score": 45,
            "category": "regular"
        },
        {
            "id": "U9",
            "trust_score": 44,
            "category": "regular"
        },
        {
            "id": "U10",
            "trust_score": 30,
            "category": "regular"
        },
        {
            "id": "U11",
            "trust_score": 25,
            "category": "regular"
        },
        {
            "id": "U12",
            "trust_score": 20,
            "category": "regular"
        },
        {
            "id": "U13",
            "trust_score": 15,
            "category": "regular"
        },
        {
            "id": "U14",
            "trust_score": 10,
            "category": "regular"
        },
        {
            "id": "U15",
            "trust_score": 5,
            "category": "regular"
        },
        {
            "id": "U16",
            "trust_score": 0,
            "category": "regular"
        },
        {
            "id": "U17",
            "trust_score": 18,
            "category": "regular"
        },
        {
            "id": "U18",
            "trust_score": 47,
            "category": "regular"
        },
        {
            "id": "U19",
            "trust_score": 32,
            "category": "regular"
        }
    ],
    "edges": [
        {
            "from": "U0",
            "to": "U4"
        },
        {
            "from": "U0",
            "to": "U5"
        },
        {
            "from": "U0",
            "to": "U6"
        },
        {
            "from": "U0",
            "to": "U7"
        },
        {
            "from": "U0",
            "to": "U8"
        },
        {
            "from": "U1",
            "to": "U4"
        },
        {
            "from": "U1",
            "to": "U5"
        },
        {
            "from": "U1",
            "to": "U6"
        },
        {
            "from": "U1",
            "to": "U7"
        },
        {
            "from": "U1",
            "to": "U9"
        },
        {
            "from": "U2",
            "to": "U4"
        },
        {
            "from": "U2",
            "to": "U5"
        },
        {
            "from": "U2",
            "to": "U6"
        },
        {
            "from": "U2",
            "to": "U7"
        },
        {
            "from": "U2",
            "to": "U10"
        },
        {
            "from": "U3",
            "to": "U4"
        },
        {
            "from": "U3",
            "to": "U5"
        },
        {
            "from": "U3",
            "to": "U6"
        },
        {
            "from": "U3",
            "to": "U7"
        },
        {
            "from": "U3",
            "to": "U11"
        },
        {
            "from": "U4",
            "to": "U8"
        },
        {
            "from": "U4",
            "to": "U9"
        },
        {
            "from": "U4",
            "to": "U10"
        },
        {
            "from": "U4",
            "to": "U14"
        },
        {
            "from": "U4",
            "to": "U18"
        },
        {
            "from": "U5",
            "to": "U9"
        },
        {
            "from": "U5",
            "to": "U10"
        },
        {
            "from": "U5",
            "to": "U11"
        },
        {
            "from": "U5",
            "to": "U15"
        },
        {
            "from": "U5",
            "to": "U19"
        },
        {
            "from": "U6",
            "to": "U10"
        },
        {
            "from": "U6",
            "to": "U11"
        },
        {
            "from": "U6",
            "to": "U12"
        },
        {
            "from": "U6",
            "to": "U16"
        },
        {
            "from": "U7",
            "to": "U11"
        },
        {
            "from": "U7",
            "to": "U12"
        },
        {
            "from": "U7",
            "to": "U13"
        },
        {
            "from": "U7",
            "to": "U17"
        }
    ],
    "result": true,
    "fullOutput": {
        "valid_no_self_loops": true,
        "valid_celebrity_outgoing": true,
        "valid_regular_to_expert": true,
        "valid_acyclic": true,
        "valid_user_attributes": true,
        "valid_edge_structure": true,
        "valid_total_users": true,
        "valid_categories": true,
        "valid_trust_scores": true,
        "errors": []
    }
}